mdpow_molconfgen-0.3.0a1.dist-info/licenses/LICENSE
molconfgen/__init__.py
molconfgen/analyze.py
molconfgen/chem.py
molconfgen/output.py
molconfgen/sampler.py
molconfgen/workflows.py
molconfgen/data/README.md
molconfgen/data/__init__.py
molconfgen/data/files.py
molconfgen/data/V36-methylacetate/V36-methylacetate.itp
molconfgen/data/V36-methylacetate/V36.pdb
molconfgen/data/V36-methylacetate/V36.top
molconfgen/data/V36-methylacetate/V36_structure.png
molconfgen/data/V39-butylacetate/V39-butylacetate.itp
molconfgen/data/V39-butylacetate/V39-butylacetate.pdb
molconfgen/data/V39-butylacetate/V39.top
molconfgen/data/V39-butylacetate/V39_structure.png
molconfgen/data/V46-2-methyl-1-nitrobenzene/V46-2-methyl-1-nitrobenzene.itp
molconfgen/data/V46-2-methyl-1-nitrobenzene/V46-2-methyl-1-nitrobenzene.mol2
molconfgen/data/V46-2-methyl-1-nitrobenzene/V46-2-methyl-1-nitrobenzene.pdb
molconfgen/data/V46-2-methyl-1-nitrobenzene/V46.png
molconfgen/data/V46-2-methyl-1-nitrobenzene/V46.top
molconfgen/tests/__init__.py
molconfgen/tests/test_analyze.py
molconfgen/tests/test_chem.py
molconfgen/tests/test_molconfgen.py
molconfgen/tests/test_sampler.py
molconfgen/tests/test_workflows.py
mdpow_molconfgen-0.3.0a1.dist-info/METADATA
mdpow_molconfgen-0.3.0a1.dist-info/WHEEL
mdpow_molconfgen-0.3.0a1.dist-info/top_level.txt
mdpow_molconfgen-0.3.0a1.dist-info/RECORD
