Metadata-Version: 2.4
Name: mdpow-molconfgen
Version: 0.3.0a1
Summary: Generation of conformers of small molecules.
Author-email: Oliver Beckstein <orbeckst@gmail.com>
Maintainer-email: Oliver Beckstein <orbeckst@gmail.com>
License-Expression: GPL-2.0-or-later
Project-URL: source, https://github.com/becksteinlab/mdpow-molconfgen
Project-URL: documentation, https://mdpow-molconfgen.readthedocs.io
Keywords: molecular simulations
Requires-Python: >=3.9
License-File: LICENSE
Requires-Dist: MDAnalysis>=2.0.0
Requires-Dist: pyedr
Requires-Dist: rdkit
Requires-Dist: numpy
Requires-Dist: tqdm
Requires-Dist: gromacswrapper
Provides-Extra: test
Requires-Dist: pytest>=6.0; extra == "test"
Requires-Dist: pytest-xdist>=2.5; extra == "test"
Requires-Dist: pytest-cov>=3.0; extra == "test"
Provides-Extra: doc
Requires-Dist: sphinx; extra == "doc"
Requires-Dist: sphinx_rtd_theme; extra == "doc"
Dynamic: license-file
